iluvatar_build_cli/__init__.py
iluvatar_build_cli/cli.py
iluvatar_build_cli/docker_builder.py
iluvatar_build_cli/runtime_handler/__init__.py
iluvatar_build_cli/runtime_handler/base.py
iluvatar_build_cli/runtime_handler/python/__init__.py
iluvatar_build_cli/runtime_handler/python/config.py
iluvatar_build_cli/runtime_handler/python/handler.py
iluvatar_build_cli/runtime_handler/python/validator.py
iluvatar_build_cli/templates/Dockerfile.template
py2lambda-1.0.0.dist-info/METADATA
py2lambda-1.0.0.dist-info/WHEEL
py2lambda-1.0.0.dist-info/entry_points.txt
py2lambda-1.0.0.dist-info/top_level.txt
py2lambda-1.0.0.dist-info/RECORD
